scraper/__init__.py
scraper/base.py
scraper/py.typed
scraper_api-0.1.1b0.dist-info/WHEEL
scraper_api-0.1.1b0.dist-info/METADATA
scraper_api-0.1.1b0.dist-info/RECORD
