Metadata-Version: 2.1
Name: scraper-api
Version: 0.1.1b0
Summary: CI/CD pipelines for scraper library
Home-page: https://github.com/danik-tro/scraper-ci-cd-library
Author: Daniil Trotsenko
Author-email: daniil.trotsenko.dev@gmail.com
Maintainer: Daniil Trotsenko
Maintainer-email: daniil.trotsenko.dev@gmail.com
Requires-Python: >=3.10,<4.0
Classifier: Programming Language :: Python :: 3
Classifier: Programming Language :: Python :: 3.10
Classifier: Topic :: Software Development :: Build Tools
Classifier: Topic :: Software Development :: Libraries :: Python Modules
Requires-Dist: requests (>=2.28.1,<3.0.0)
Project-URL: Documentation, https://danik-tro.github.io/scraper-ci-cd-library/
Project-URL: Repository, https://github.com/danik-tro/scraper-ci-cd-library
